pip_compile_multi-3.2.2.dist-info/licenses/AUTHORS.rst
pip_compile_multi-3.2.2.dist-info/licenses/LICENSE.txt
pipcompilemulti/__init__.py
pipcompilemulti/actions.py
pipcompilemulti/cli_v1.py
pipcompilemulti/cli_v2.py
pipcompilemulti/config.py
pipcompilemulti/deduplicate.py
pipcompilemulti/dependency.py
pipcompilemulti/discover.py
pipcompilemulti/environment.py
pipcompilemulti/options.py
pipcompilemulti/utils.py
pipcompilemulti/verify.py
pipcompilemulti/features/__init__.py
pipcompilemulti/features/add_hashes.py
pipcompilemulti/features/annotate_index.py
pipcompilemulti/features/autoresolve.py
pipcompilemulti/features/backtracking.py
pipcompilemulti/features/base.py
pipcompilemulti/features/base_dir.py
pipcompilemulti/features/build_isolation.py
pipcompilemulti/features/compatible.py
pipcompilemulti/features/controller.py
pipcompilemulti/features/emit_trusted_host.py
pipcompilemulti/features/extra_index_url.py
pipcompilemulti/features/file_extensions.py
pipcompilemulti/features/forbid_post.py
pipcompilemulti/features/forward.py
pipcompilemulti/features/header.py
pipcompilemulti/features/limit_in_paths.py
pipcompilemulti/features/live_output.py
pipcompilemulti/features/skip_constraint_comments.py
pipcompilemulti/features/strip_extras.py
pipcompilemulti/features/unsafe.py
pipcompilemulti/features/upgrade.py
pipcompilemulti/features/use_cache.py
pipcompilemulti/features/use_uv.py
pip_compile_multi-3.2.2.dist-info/METADATA
pip_compile_multi-3.2.2.dist-info/WHEEL
pip_compile_multi-3.2.2.dist-info/entry_points.txt
pip_compile_multi-3.2.2.dist-info/top_level.txt
pip_compile_multi-3.2.2.dist-info/RECORD
