Metadata-Version: 2.4
Name: pip_compile_multi
Version: 3.2.2
Summary: Compile multiple requirements files to lock dependency versions
Home-page: https://github.com/peterdemin/pip-compile-multi
Author: Peter Demin
Author-email: peterdemin@gmail.com
License: MIT
Keywords: pip-compile-multi
Classifier: Development Status :: 5 - Production/Stable
Classifier: Intended Audience :: Developers
Classifier: Natural Language :: English
Classifier: Environment :: Console
Classifier: Programming Language :: Python :: 3.9
Classifier: Programming Language :: Python :: 3.10
Classifier: Programming Language :: Python :: 3.11
Classifier: Programming Language :: Python :: 3.12
Classifier: Programming Language :: Python :: 3.13
Classifier: Programming Language :: Python :: Implementation :: CPython
Classifier: Programming Language :: Python :: Implementation :: PyPy
Classifier: Topic :: Utilities
Requires-Python: ~=3.9
License-File: LICENSE.txt
License-File: AUTHORS.rst
Requires-Dist: click
Requires-Dist: pip-tools>=6.8.0
Requires-Dist: toposort
Dynamic: author
Dynamic: author-email
Dynamic: classifier
Dynamic: description
Dynamic: home-page
Dynamic: keywords
Dynamic: license
Dynamic: license-file
Dynamic: requires-dist
Dynamic: requires-python
Dynamic: summary
